[
    {
        "Report": "https://campfin.dallascityhall.com/FinalReports/tec0000001746_20190404_113156.pdf",
        "S/R": "https://campfin.dallascityhall.com/FinalReports/srp0000001746_20190404_113156.pdf",
        "Name": ", Campaign to Elect",
        "Contact_Type": "Expenditure",
        "ReportId": "1746",
        "Report_Type": "30th Day Before General Election 2019",
        "Amount": 1350.0,
        "Recipient": "Carolyn Arnold",
        "Transaction_Date": "3/20/2019",
        "Date_Time_Submitted": "4/4/2019 11:31:56 AM",
        "Address": "3440  S Polk\nDallas, TX    75224"
    },
    {
        "Report": "https://campfin.dallascityhall.com/FinalReports/tec0000001746_20190404_113156.pdf",
        "S/R": "https://campfin.dallascityhall.com/FinalReports/srp0000001746_20190404_113156.pdf",
        "Name": ", Crickett",
        "Contact_Type": "Expenditure",
        "ReportId": "1746",
        "Report_Type": "30th Day Before General Election 2019",
        "Amount": 120.0,
        "Recipient": "Carolyn Arnold",
        "Transaction_Date": "3/20/2019",
        "Date_Time_Submitted": "4/4/2019 11:31:56 AM",
        "Address": "3306  W CampWisdom\nDallas, TX    75232"
    },
    {
        "Report": "N/A",
        "S/R": "https://campfin.dallascityhall.com/FinalReports/srp0000002693_20230717_164731.pdf",
        "Name": "Armstrong, Cassandra",
        "Contact_Type": "Expenditure",
        "ReportId": "2693",
        "Report_Type": "July 15: Semi-Annual 2023",
        "Amount": 1934.0,
        "Recipient": "Carolyn Arnold",
        "Transaction_Date": "5/5/2023",
        "Date_Time_Submitted": "7/17/2023 4:47:31 PM",
        "Address": "1801  Wheatland\nDallas, TX    75241"
    },
    {
        "Report": "N/A",
        "S/R": "https://campfin.dallascityhall.com/FinalReports/srp0000002693_20230717_164731.pdf",
        "Name": "Belt, James",
        "Contact_Type": "Expenditure",
        "ReportId": "2693",
        "Report_Type": "July 15: Semi-Annual 2023",
        "Amount": 405.0,
        "Recipient": "Carolyn Arnold",
        "Transaction_Date": "4/30/2023",
        "Date_Time_Submitted": "7/17/2023 4:47:31 PM",
        "Address": "400  Zang\nDallas, TX    75208"
    },
    {
        "Report": "https://campfin.dallascityhall.com/FinalReports/caf0000001893_20230207_171146.pdf",
        "S/R": "https://campfin.dallascityhall.com/FinalReports/src0000001893_20230207_171146.pdf",
        "Name": "Blair, Darrell",
        "Contact_Type": "Expenditure",
        "ReportId": "1893",
        "Report_Type": "July 15: Semi-Annual 2019\nCorrection Affidavit",
        "Amount": 500.0,
        "Recipient": "Carolyn Arnold",
        "Transaction_Date": "6/12/2019",
        "Date_Time_Submitted": "2/7/2023 5:12:16 PM",
        "Address": "PO Box 380017\nDuncanville, TX    75183"
    },
    {
        "Report": "N/A",
        "S/R": "https://campfin.dallascityhall.com/FinalReports/srp0000002572_20230406_130322.pdf",
        "Name": "Bouck, Jeff",
        "Contact_Type": "Expenditure",
        "ReportId": "2572",
        "Report_Type": "30th Day Before General Election 2023",
        "Amount": 400.0,
        "Recipient": "Carolyn Arnold",
        "Transaction_Date": "2/6/2023",
        "Date_Time_Submitted": "4/6/2023 1:03:22 PM",
        "Address": "103  NW 14th\nGrand Prarie, TX    75050"
    },
    {
        "Report": "N/A",
        "S/R": "https://campfin.dallascityhall.com/FinalReports/srp0000002330_20210715_163638.pdf",
        "Name": "Bullard, Zach",
        "Contact_Type": "Expenditure",
        "ReportId": "2330",
        "Report_Type": "July 15: Semi-Annual 2021",
        "Amount": 2500.0,
        "Recipient": "Carolyn Arnold",
        "Transaction_Date": "6/2/2021",
        "Date_Time_Submitted": "7/15/2021 4:36:38 PM",
        "Address": "2710  Routh Street\nDallas, TX    75082"
    },
    {
        "Report": "N/A",
        "S/R": "https://campfin.dallascityhall.com/FinalReports/srp0000002693_20230717_164731.pdf",
        "Name": "Bullard, Zach",
        "Contact_Type": "Expenditure",
        "ReportId": "2693",
        "Report_Type": "July 15: Semi-Annual 2023",
        "Amount": 1000.0,
        "Recipient": "Carolyn Arnold",
        "Transaction_Date": "5/2/2023",
        "Date_Time_Submitted": "7/17/2023 4:47:31 PM",
        "Address": "2710  Routh\nDallas, TX    75082"
    },
    {
        "Report": "N/A",
        "S/R": "https://campfin.dallascityhall.com/FinalReports/srp0000002649_20230428_164754.pdf",
        "Name": "Clear Channel",
        "Contact_Type": "Expenditure",
        "ReportId": "2649",
        "Report_Type": "8th Day Before General Election 2023",
        "Amount": 3800.0,
        "Recipient": "Carolyn Arnold",
        "Transaction_Date": "4/24/2023",
        "Date_Time_Submitted": "4/28/2023 4:47:54 PM",
        "Address": "3700  Randol Mill\nArlington, TX    76011"
    },
    {
        "Report": "N/A",
        "S/R": "https://campfin.dallascityhall.com/FinalReports/srp0000002330_20210715_163638.pdf",
        "Name": "Collins, Rod",
        "Contact_Type": "Expenditure",
        "ReportId": "2330",
        "Report_Type": "July 15: Semi-Annual 2021",
        "Amount": 2075.0,
        "Recipient": "Carolyn Arnold",
        "Transaction_Date": "6/1/2021",
        "Date_Time_Submitted": "7/15/2021 4:36:38 PM",
        "Address": "4310  Buena Vista\nDallas, TX    75205"
    },
    {
        "Report": "N/A",
        "S/R": "https://campfin.dallascityhall.com/FinalReports/srp0000002330_20210715_163638.pdf",
        "Name": "Company, MMS",
        "Contact_Type": "Expenditure",
        "ReportId": "2330",
        "Report_Type": "July 15: Semi-Annual 2021",
        "Amount": 4108.0,
        "Recipient": "Carolyn Arnold",
        "Transaction_Date": "6/15/2021",
        "Date_Time_Submitted": "7/15/2021 4:36:38 PM",
        "Address": "217  N. IH35\nDeSoto, TX    75115"
    },
    {
        "Report": "N/A",
        "S/R": "https://campfin.dallascityhall.com/FinalReports/srp0000002330_20210715_163638.pdf",
        "Name": "Dalton, Jeff",
        "Contact_Type": "Expenditure",
        "ReportId": "2330",
        "Report_Type": "July 15: Semi-Annual 2021",
        "Amount": 1500.0,
        "Recipient": "Carolyn Arnold",
        "Transaction_Date": "6/5/2021",
        "Date_Time_Submitted": "7/15/2021 4:36:38 PM",
        "Address": "8552  Royal County Down Dr\nMcKinney, TX    75070"
    },
    {
        "Report": "N/A",
        "S/R": "https://campfin.dallascityhall.com/FinalReports/srp0000002572_20230406_130322.pdf",
        "Name": "Dalton, Jeff",
        "Contact_Type": "Expenditure",
        "ReportId": "2572",
        "Report_Type": "30th Day Before General Election 2023",
        "Amount": 2000.0,
        "Recipient": "Carolyn Arnold",
        "Transaction_Date": "2/1/2023",
        "Date_Time_Submitted": "4/6/2023 1:03:22 PM",
        "Address": "8552  Royal County Down\nMcKinney, TX    75070"
    },
    {
        "Report": "N/A",
        "S/R": "https://campfin.dallascityhall.com/FinalReports/srp0000002572_20230406_130322.pdf",
        "Name": "Dalton, Jeff",
        "Contact_Type": "Expenditure",
        "ReportId": "2572",
        "Report_Type": "30th Day Before General Election 2023",
        "Amount": 1500.0,
        "Recipient": "Carolyn Arnold",
        "Transaction_Date": "3/20/2023",
        "Date_Time_Submitted": "4/6/2023 1:03:22 PM",
        "Address": "8552  Royal CountyDown\nDallas, TX    75050"
    },
    {
        "Report": "N/A",
        "S/R": "https://campfin.dallascityhall.com/FinalReports/srp0000002649_20230428_164754.pdf",
        "Name": "Democracy Toolbox",
        "Contact_Type": "Expenditure",
        "ReportId": "2649",
        "Report_Type": "8th Day Before General Election 2023",
        "Amount": 2000.0,
        "Recipient": "Carolyn Arnold",
        "Transaction_Date": "4/5/2023",
        "Date_Time_Submitted": "4/28/2023 4:47:54 PM",
        "Address": "8552  Royal County Down\nMcKINNEY, TX    75070"
    },
    {
        "Report": "https://campfin.dallascityhall.com/FinalReports/caf0000001893_20230207_171146.pdf",
        "S/R": "https://campfin.dallascityhall.com/FinalReports/src0000001893_20230207_171146.pdf",
        "Name": "DEPOT, HOME",
        "Contact_Type": "Expenditure",
        "ReportId": "1893",
        "Report_Type": "July 15: Semi-Annual 2019\nCorrection Affidavit",
        "Amount": 120.0,
        "Recipient": "Carolyn Arnold",
        "Transaction_Date": "6/6/2019",
        "Date_Time_Submitted": "2/7/2023 5:12:16 PM",
        "Address": "373  E FM 1382\nDallas, TX    75104"
    },
    {
        "Report": "N/A",
        "S/R": "https://campfin.dallascityhall.com/FinalReports/srp0000002185_20210401_165710.pdf",
        "Name": "Echols, Reilly",
        "Contact_Type": "Expenditure",
        "ReportId": "2185",
        "Report_Type": "30th Day Before General Election 2021",
        "Amount": 560.0,
        "Recipient": "Carolyn KIng Arnold",
        "Transaction_Date": "3/15/2021",
        "Date_Time_Submitted": "4/1/2021 4:57:10 PM",
        "Address": "1710  Harwood\nDallas, TX    75215"
    },
    {
        "Report": "N/A",
        "S/R": "https://campfin.dallascityhall.com/FinalReports/srp0000002330_20210715_163638.pdf",
        "Name": "Echols, Steve",
        "Contact_Type": "Expenditure",
        "ReportId": "2330",
        "Report_Type": "July 15: Semi-Annual 2021",
        "Amount": 2115.0,
        "Recipient": "Carolyn Arnold",
        "Transaction_Date": "5/28/2021",
        "Date_Time_Submitted": "7/15/2021 4:36:38 PM",
        "Address": "1710  Harwood\nDallas, TX    75215"
    },
    {
        "Report": "N/A",
        "S/R": "https://campfin.dallascityhall.com/FinalReports/srp0000002330_20210715_163638.pdf",
        "Name": "English, Jack",
        "Contact_Type": "Expenditure",
        "ReportId": "2330",
        "Report_Type": "July 15: Semi-Annual 2021",
        "Amount": 700.0,
        "Recipient": "Carolyn Arnold",
        "Transaction_Date": "6/5/2021",
        "Date_Time_Submitted": "7/15/2021 4:36:38 PM",
        "Address": "1013  Farmington\nIndian Trail, NC    28079"
    },
    {
        "Report": "https://campfin.dallascityhall.com/FinalReports/caf0000001893_20230207_171146.pdf",
        "S/R": "https://campfin.dallascityhall.com/FinalReports/src0000001893_20230207_171146.pdf",
        "Name": "Fain, Daphne",
        "Contact_Type": "Expenditure",
        "ReportId": "1893",
        "Report_Type": "July 15: Semi-Annual 2019\nCorrection Affidavit",
        "Amount": 324.0,
        "Recipient": "Carolyn Arnold",
        "Transaction_Date": "6/18/2019",
        "Date_Time_Submitted": "2/7/2023 5:12:16 PM",
        "Address": "217  N. Interstate\nDeSoto, TX    75115"
    },
    {
        "Report": "https://campfin.dallascityhall.com/FinalReports/tec0000001746_20190404_113156.pdf",
        "S/R": "https://campfin.dallascityhall.com/FinalReports/srp0000001746_20190404_113156.pdf",
        "Name": "Foster, Phil",
        "Contact_Type": "Expenditure",
        "ReportId": "1746",
        "Report_Type": "30th Day Before General Election 2019",
        "Amount": 150.0,
        "Recipient": "Carolyn Arnold",
        "Transaction_Date": "3/20/2019",
        "Date_Time_Submitted": "4/4/2019 11:31:56 AM",
        "Address": "3440  Polk\nDallas, TX    75224"
    },
    {
        "Report": "https://campfin.dallascityhall.com/FinalReports/tec0000001746_20190404_113156.pdf",
        "S/R": "https://campfin.dallascityhall.com/FinalReports/srp0000001746_20190404_113156.pdf",
        "Name": "Foster, Phil",
        "Contact_Type": "Expenditure",
        "ReportId": "1746",
        "Report_Type": "30th Day Before General Election 2019",
        "Amount": 2000.0,
        "Recipient": "Carolyn Arnold",
        "Transaction_Date": "3/25/2019",
        "Date_Time_Submitted": "4/4/2019 11:31:56 AM",
        "Address": "3440  S. Polk\nDallas, TX    75224"
    },
    {
        "Report": "https://campfin.dallascityhall.com/FinalReports/tec0000001848_20190426_161641.pdf",
        "S/R": "https://campfin.dallascityhall.com/FinalReports/srp0000001848_20190426_161641.pdf",
        "Name": "Foster, Phil",
        "Contact_Type": "Expenditure",
        "ReportId": "1848",
        "Report_Type": "8th Day Before General Election 2019",
        "Amount": 600.0,
        "Recipient": "Carolyn Arnold",
        "Transaction_Date": "4/16/2019",
        "Date_Time_Submitted": "4/26/2019 4:16:41 PM",
        "Address": "3440  S. Polk\nDallas, TX    75224"
    },
    {
        "Report": "https://campfin.dallascityhall.com/FinalReports/caf0000001893_20230207_171146.pdf",
        "S/R": "https://campfin.dallascityhall.com/FinalReports/src0000001893_20230207_171146.pdf",
        "Name": "Foster, Phil",
        "Contact_Type": "Expenditure",
        "ReportId": "1893",
        "Report_Type": "July 15: Semi-Annual 2019\nCorrection Affidavit",
        "Amount": 2400.0,
        "Recipient": "Carolyn Arnold",
        "Transaction_Date": "6/10/2019",
        "Date_Time_Submitted": "2/7/2023 5:12:16 PM",
        "Address": "3440  S. Polk\nDallas, TX    75224"
    },
    {
        "Report": "https://campfin.dallascityhall.com/FinalReports/caf0000001893_20230207_171146.pdf",
        "S/R": "https://campfin.dallascityhall.com/FinalReports/src0000001893_20230207_171146.pdf",
        "Name": "Foster, Phil",
        "Contact_Type": "Expenditure",
        "ReportId": "1893",
        "Report_Type": "July 15: Semi-Annual 2019\nCorrection Affidavit",
        "Amount": 2500.0,
        "Recipient": "Carolyn Arnold",
        "Transaction_Date": "6/15/2019",
        "Date_Time_Submitted": "2/7/2023 5:12:16 PM",
        "Address": "3440  S. Polk\nDallas, TX    75224"
    },
    {
        "Report": "N/A",
        "S/R": "https://campfin.dallascityhall.com/FinalReports/srp0000002330_20210715_163638.pdf",
        "Name": "Group, Nealy",
        "Contact_Type": "Expenditure",
        "ReportId": "2330",
        "Report_Type": "July 15: Semi-Annual 2021",
        "Amount": 1500.0,
        "Recipient": "Carolyn Arnold",
        "Transaction_Date": "5/28/2021",
        "Date_Time_Submitted": "7/15/2021 4:36:38 PM",
        "Address": "PO Box 191803\nDallas, TX    75219"
    },
    {
        "Report": "N/A",
        "S/R": "https://campfin.dallascityhall.com/FinalReports/srp0000002693_20230717_164731.pdf",
        "Name": "Heffner, Shane",
        "Contact_Type": "Expenditure",
        "ReportId": "2693",
        "Report_Type": "July 15: Semi-Annual 2023",
        "Amount": 200.0,
        "Recipient": "Carolyn Arnold",
        "Transaction_Date": "4/30/2023",
        "Date_Time_Submitted": "7/17/2023 4:47:31 PM",
        "Address": "8552  Royal Doulton\nMcKinney, TX    75070"
    },
    {
        "Report": "https://campfin.dallascityhall.com/FinalReports/caf0000001893_20230207_171146.pdf",
        "S/R": "https://campfin.dallascityhall.com/FinalReports/src0000001893_20230207_171146.pdf",
        "Name": "Hunt, Doug",
        "Contact_Type": "Expenditure",
        "ReportId": "1893",
        "Report_Type": "July 15: Semi-Annual 2019\nCorrection Affidavit",
        "Amount": 500.0,
        "Recipient": "Carolyn Arnold",
        "Transaction_Date": "6/12/2019",
        "Date_Time_Submitted": "2/7/2023 5:12:16 PM",
        "Address": "3404  N. Interstate\nLancaster, TX    75134"
    },
    {
        "Report": "N/A",
        "S/R": "https://campfin.dallascityhall.com/FinalReports/srp0000002693_20230717_164731.pdf",
        "Name": "Jackson, Nethal",
        "Contact_Type": "Expenditure",
        "ReportId": "2693",
        "Report_Type": "July 15: Semi-Annual 2023",
        "Amount": 360.0,
        "Recipient": "Carolyn Arnold",
        "Transaction_Date": "5/3/2023",
        "Date_Time_Submitted": "7/17/2023 4:47:31 PM",
        "Address": "2815  ToLuca\nDallas, TX    75244"
    },
    {
        "Report": "N/A",
        "S/R": "https://campfin.dallascityhall.com/FinalReports/srp0000002330_20210715_163638.pdf",
        "Name": "Jackson, Nethal",
        "Contact_Type": "Expenditure",
        "ReportId": "2330",
        "Report_Type": "July 15: Semi-Annual 2021",
        "Amount": 4000.0,
        "Recipient": "Carolyn Arnold",
        "Transaction_Date": "6/5/2021",
        "Date_Time_Submitted": "7/15/2021 4:36:38 PM",
        "Address": "2851  Toluca\nDallas, TX    75224"
    },
    {
        "Report": "N/A",
        "S/R": "https://campfin.dallascityhall.com/FinalReports/srp0000002572_20230406_130322.pdf",
        "Name": "Jackson, Nethal",
        "Contact_Type": "Expenditure",
        "ReportId": "2572",
        "Report_Type": "30th Day Before General Election 2023",
        "Amount": 1500.0,
        "Recipient": "Carolyn Arnold",
        "Transaction_Date": "2/20/2023",
        "Date_Time_Submitted": "4/6/2023 1:03:22 PM",
        "Address": "2851  Toluca\nDallas, TX    75224"
    },
    {
        "Report": "N/A",
        "S/R": "https://campfin.dallascityhall.com/FinalReports/srp0000002572_20230406_130322.pdf",
        "Name": "Jackson, Nethal",
        "Contact_Type": "Expenditure",
        "ReportId": "2572",
        "Report_Type": "30th Day Before General Election 2023",
        "Amount": 2451.0,
        "Recipient": "Carolyn Arnold",
        "Transaction_Date": "3/15/2023",
        "Date_Time_Submitted": "4/6/2023 1:03:22 PM",
        "Address": "2851  Toluca\nDallas, TX    75224"
    },
    {
        "Report": "N/A",
        "S/R": "https://campfin.dallascityhall.com/FinalReports/srp0000002693_20230717_164731.pdf",
        "Name": "Jackson, Nethal",
        "Contact_Type": "Expenditure",
        "ReportId": "2693",
        "Report_Type": "July 15: Semi-Annual 2023",
        "Amount": 4300.0,
        "Recipient": "Carolyn Arnold",
        "Transaction_Date": "5/6/2023",
        "Date_Time_Submitted": "7/17/2023 4:47:31 PM",
        "Address": "2851  Toluca\nDallas, TX    75224"
    },
    {
        "Report": "N/A",
        "S/R": "https://campfin.dallascityhall.com/FinalReports/srp0000002185_20210401_165710.pdf",
        "Name": "Jackson, Nethal",
        "Contact_Type": "Expenditure",
        "ReportId": "2185",
        "Report_Type": "30th Day Before General Election 2021",
        "Amount": 2122.0,
        "Recipient": "Carolyn KIng Arnold",
        "Transaction_Date": "3/21/2021",
        "Date_Time_Submitted": "4/1/2021 4:57:10 PM",
        "Address": "2851  Touloca\nDallas, TX    75224"
    },
    {
        "Report": "N/A",
        "S/R": "https://campfin.dallascityhall.com/FinalReports/srp0000002185_20210401_165710.pdf",
        "Name": "Jay, Jay",
        "Contact_Type": "Expenditure",
        "ReportId": "2185",
        "Report_Type": "30th Day Before General Election 2021",
        "Amount": 568.0,
        "Recipient": "Carolyn KIng Arnold",
        "Transaction_Date": "3/12/2021",
        "Date_Time_Submitted": "4/1/2021 4:57:10 PM",
        "Address": "103  NW 14th\nGrand Prairie, TX    75050"
    },
    {
        "Report": "N/A",
        "S/R": "https://campfin.dallascityhall.com/FinalReports/srp0000002330_20210715_163638.pdf",
        "Name": "Karay Event Planning",
        "Contact_Type": "Expenditure",
        "ReportId": "2330",
        "Report_Type": "July 15: Semi-Annual 2021",
        "Amount": 2500.0,
        "Recipient": "Carolyn Arnold",
        "Transaction_Date": "6/4/2021",
        "Date_Time_Submitted": "7/15/2021 4:36:38 PM",
        "Address": "PO Box 764978\nDallas, TX    75376"
    },
    {
        "Report": "N/A",
        "S/R": "https://campfin.dallascityhall.com/FinalReports/srp0000002185_20210401_165710.pdf",
        "Name": "Keever, LaShun",
        "Contact_Type": "Expenditure",
        "ReportId": "2185",
        "Report_Type": "30th Day Before General Election 2021",
        "Amount": 620.0,
        "Recipient": "Carolyn KIng Arnold",
        "Transaction_Date": "3/20/2021",
        "Date_Time_Submitted": "4/1/2021 4:57:10 PM",
        "Address": "1111  James\nLancaster, TX    75115"
    },
    {
        "Report": "N/A",
        "S/R": "https://campfin.dallascityhall.com/FinalReports/srp0000002330_20210715_163638.pdf",
        "Name": "Keglar, Freda",
        "Contact_Type": "Expenditure",
        "ReportId": "2330",
        "Report_Type": "July 15: Semi-Annual 2021",
        "Amount": 2000.0,
        "Recipient": "Carolyn Arnold",
        "Transaction_Date": "6/7/2021",
        "Date_Time_Submitted": "7/15/2021 4:36:38 PM",
        "Address": "1626  Mentor\nDallas, TX    75216"
    },
    {
        "Report": "https://campfin.dallascityhall.com/FinalReports/caf0000001893_20230207_171146.pdf",
        "S/R": "https://campfin.dallascityhall.com/FinalReports/src0000001893_20230207_171146.pdf",
        "Name": "Lacy, Lance",
        "Contact_Type": "Treasurer of Committee",
        "ReportId": "1893",
        "Report_Type": "July 15: Semi-Annual 2019\nCorrection Affidavit",
        "Amount": 0.0,
        "Recipient": "Carolyn Arnold",
        "Transaction_Date": "7/15/2019",
        "Date_Time_Submitted": "2/7/2023 5:12:16 PM",
        "Address": "PO Box 2246\nAustin, TX    78768"
    },
    {
        "Report": "N/A",
        "S/R": "https://campfin.dallascityhall.com/FinalReports/srp0000002693_20230717_164731.pdf",
        "Name": "Laney, Edrick",
        "Contact_Type": "Expenditure",
        "ReportId": "2693",
        "Report_Type": "July 15: Semi-Annual 2023",
        "Amount": 2390.0,
        "Recipient": "Carolyn Arnold",
        "Transaction_Date": "4/27/2023",
        "Date_Time_Submitted": "7/17/2023 4:47:31 PM",
        "Address": "204  E. Pleasant Run\nDallas, TX    75146"
    },
    {
        "Report": "N/A",
        "S/R": "https://campfin.dallascityhall.com/FinalReports/srp0000002693_20230717_164731.pdf",
        "Name": "McGee, Andrew",
        "Contact_Type": "Expenditure",
        "ReportId": "2693",
        "Report_Type": "July 15: Semi-Annual 2023",
        "Amount": 2100.0,
        "Recipient": "Carolyn Arnold",
        "Transaction_Date": "4/27/2023",
        "Date_Time_Submitted": "7/17/2023 4:47:31 PM",
        "Address": "920  Channing Circle\nDallas, TX    75224"
    },
    {
        "Report": "https://campfin.dallascityhall.com/FinalReports/tec0000001746_20190404_113156.pdf",
        "S/R": "https://campfin.dallascityhall.com/FinalReports/srp0000001746_20190404_113156.pdf",
        "Name": "Miller, D.",
        "Contact_Type": "Expenditure",
        "ReportId": "1746",
        "Report_Type": "30th Day Before General Election 2019",
        "Amount": 365.0,
        "Recipient": "Carolyn Arnold",
        "Transaction_Date": "3/15/2019",
        "Date_Time_Submitted": "4/4/2019 11:31:56 AM",
        "Address": "1026  Zang\nDallas, TX    75208"
    },
    {
        "Report": "https://campfin.dallascityhall.com/FinalReports/tec0000001848_20190426_161641.pdf",
        "S/R": "https://campfin.dallascityhall.com/FinalReports/srp0000001848_20190426_161641.pdf",
        "Name": "Miller, Don",
        "Contact_Type": "Expenditure",
        "ReportId": "1848",
        "Report_Type": "8th Day Before General Election 2019",
        "Amount": 800.0,
        "Recipient": "Carolyn Arnold",
        "Transaction_Date": "4/23/2019",
        "Date_Time_Submitted": "4/26/2019 4:16:41 PM",
        "Address": "1026  Zang\nDallas, TX    75208"
    },
    {
        "Report": "N/A",
        "S/R": "https://campfin.dallascityhall.com/FinalReports/srp0000002693_20230717_164731.pdf",
        "Name": "Moore, Teresa",
        "Contact_Type": "Expenditure",
        "ReportId": "2693",
        "Report_Type": "July 15: Semi-Annual 2023",
        "Amount": 3880.0,
        "Recipient": "Carolyn Arnold",
        "Transaction_Date": "4/28/2023",
        "Date_Time_Submitted": "7/17/2023 4:47:31 PM",
        "Address": "3700  Randol Mills\nArlington, TX    76011"
    },
    {
        "Report": "N/A",
        "S/R": "https://campfin.dallascityhall.com/FinalReports/srp0000002330_20210715_163638.pdf",
        "Name": "Moore, Teresa",
        "Contact_Type": "Expenditure",
        "ReportId": "2330",
        "Report_Type": "July 15: Semi-Annual 2021",
        "Amount": 600.0,
        "Recipient": "Carolyn Arnold",
        "Transaction_Date": "6/3/2021",
        "Date_Time_Submitted": "7/15/2021 4:36:38 PM",
        "Address": "PO Box 847247\nDallas, TX    75284"
    },
    {
        "Report": "N/A",
        "S/R": "https://campfin.dallascityhall.com/FinalReports/srp0000002693_20230717_164731.pdf",
        "Name": "Nealy, Kathy",
        "Contact_Type": "Expenditure",
        "ReportId": "2693",
        "Report_Type": "July 15: Semi-Annual 2023",
        "Amount": 2500.0,
        "Recipient": "Carolyn Arnold",
        "Transaction_Date": "5/1/2023",
        "Date_Time_Submitted": "7/17/2023 4:47:31 PM",
        "Address": "PO Box 191803\nDallas, TX    75219"
    },
    {
        "Report": "N/A",
        "S/R": "https://campfin.dallascityhall.com/FinalReports/srp0000002330_20210715_163638.pdf",
        "Name": "Oil, Shell",
        "Contact_Type": "Expenditure",
        "ReportId": "2330",
        "Report_Type": "July 15: Semi-Annual 2021",
        "Amount": 100.0,
        "Recipient": "Carolyn Arnold",
        "Transaction_Date": "6/5/2021",
        "Date_Time_Submitted": "7/15/2021 4:36:38 PM",
        "Address": "500  W. Kiest\nDallas, TX    75224"
    },
    {
        "Report": "N/A",
        "S/R": "https://campfin.dallascityhall.com/FinalReports/srp0000002330_20210715_163638.pdf",
        "Name": "Printing, CCCP",
        "Contact_Type": "Expenditure",
        "ReportId": "2330",
        "Report_Type": "July 15: Semi-Annual 2021",
        "Amount": 250.0,
        "Recipient": "Carolyn Arnold",
        "Transaction_Date": "5/28/2021",
        "Date_Time_Submitted": "7/15/2021 4:36:38 PM",
        "Address": "5534  Hanpton\nDallas, TX    75232"
    },
    {
        "Report": "N/A",
        "S/R": "https://campfin.dallascityhall.com/FinalReports/srp0000002649_20230428_164754.pdf",
        "Name": "REILLY ECHOLS PRINTING",
        "Contact_Type": "Expenditure",
        "ReportId": "2649",
        "Report_Type": "8th Day Before General Election 2023",
        "Amount": 1300.0,
        "Recipient": "Carolyn Arnold",
        "Transaction_Date": "4/1/2023",
        "Date_Time_Submitted": "4/28/2023 4:47:54 PM",
        "Address": "1710  HARWOOD\nDallas, TX    75215"
    },
    {
        "Report": "N/A",
        "S/R": "https://campfin.dallascityhall.com/FinalReports/srp0000002693_20230717_164731.pdf",
        "Name": "Reilly, Steve",
        "Contact_Type": "Expenditure",
        "ReportId": "2693",
        "Report_Type": "July 15: Semi-Annual 2023",
        "Amount": 1219.0,
        "Recipient": "Carolyn Arnold",
        "Transaction_Date": "5/1/2023",
        "Date_Time_Submitted": "7/17/2023 4:47:31 PM",
        "Address": "1710  South Harwood\nDallas, TX    75215"
    },
    {
        "Report": "N/A",
        "S/R": "https://campfin.dallascityhall.com/FinalReports/srp0000002330_20210715_163638.pdf",
        "Name": "Ross, Jeff",
        "Contact_Type": "Expenditure",
        "ReportId": "2330",
        "Report_Type": "July 15: Semi-Annual 2021",
        "Amount": 2001.0,
        "Recipient": "Carolyn Arnold",
        "Transaction_Date": "5/28/2021",
        "Date_Time_Submitted": "7/15/2021 4:36:38 PM",
        "Address": "9840  Monroe Dr.\nDallas, TX    75220"
    },
    {
        "Report": "N/A",
        "S/R": "https://campfin.dallascityhall.com/FinalReports/srp0000002572_20230406_130322.pdf",
        "Name": "ross, jeff",
        "Contact_Type": "Expenditure",
        "ReportId": "2572",
        "Report_Type": "30th Day Before General Election 2023",
        "Amount": 3809.04,
        "Recipient": "Carolyn Arnold",
        "Transaction_Date": "3/27/2023",
        "Date_Time_Submitted": "4/6/2023 1:03:22 PM",
        "Address": "9840  Monroe Dr\nDallas, TX    75220"
    },
    {
        "Report": "N/A",
        "S/R": "https://campfin.dallascityhall.com/FinalReports/srp0000002693_20230717_164731.pdf",
        "Name": "Stores, Walmart",
        "Contact_Type": "Expenditure",
        "ReportId": "2693",
        "Report_Type": "July 15: Semi-Annual 2023",
        "Amount": 212.0,
        "Recipient": "Carolyn Arnold",
        "Transaction_Date": "5/4/2023",
        "Date_Time_Submitted": "7/17/2023 4:47:31 PM",
        "Address": "200  Short blvd\nDallas, TX    75232"
    },
    {
        "Report": "N/A",
        "S/R": "https://campfin.dallascityhall.com/FinalReports/srp0000002185_20210401_165710.pdf",
        "Name": "Tasha, Tasha",
        "Contact_Type": "Expenditure",
        "ReportId": "2185",
        "Report_Type": "30th Day Before General Election 2021",
        "Amount": 2300.0,
        "Recipient": "Carolyn KIng Arnold",
        "Transaction_Date": "3/22/2021",
        "Date_Time_Submitted": "4/1/2021 4:57:10 PM",
        "Address": "1804  Afton\nHouston, TX    77055"
    },
    {
        "Report": "https://campfin.dallascityhall.com/FinalReports/caf0000001893_20230207_171146.pdf",
        "S/R": "https://campfin.dallascityhall.com/FinalReports/src0000001893_20230207_171146.pdf",
        "Name": "Texas Realtors PAC",
        "Contact_Type": "Expenditure",
        "ReportId": "1893",
        "Report_Type": "July 15: Semi-Annual 2019\nCorrection Affidavit",
        "Amount": 0.0,
        "Recipient": "Carolyn Arnold",
        "Transaction_Date": "7/15/2019",
        "Date_Time_Submitted": "2/7/2023 5:12:16 PM",
        "Address": "PO Box 295305\nKerrville, TX    78029"
    },
    {
        "Report": "N/A",
        "S/R": "https://campfin.dallascityhall.com/FinalReports/srp0000002693_20230717_164731.pdf",
        "Name": "Whitaker, CW",
        "Contact_Type": "Expenditure",
        "ReportId": "2693",
        "Report_Type": "July 15: Semi-Annual 2023",
        "Amount": 300.0,
        "Recipient": "Carolyn Arnold",
        "Transaction_Date": "5/3/2023",
        "Date_Time_Submitted": "7/17/2023 4:47:31 PM",
        "Address": "2130  Oak Valley Lane\nDallas, TX    75232"
    },
    {
        "Report": "N/A",
        "S/R": "https://campfin.dallascityhall.com/FinalReports/srp0000002330_20210715_163638.pdf",
        "Name": "Wireless, Crickett",
        "Contact_Type": "Expenditure",
        "ReportId": "2330",
        "Report_Type": "July 15: Semi-Annual 2021",
        "Amount": 150.0,
        "Recipient": "Carolyn Arnold",
        "Transaction_Date": "6/1/2021",
        "Date_Time_Submitted": "7/15/2021 4:36:38 PM",
        "Address": "3200  Lancaster\nDallas, TX    75216"
    },
    {
        "Report": "N/A",
        "S/R": "https://campfin.dallascityhall.com/FinalReports/srp0000002410_20220118_153432.pdf",
        "Name": "Wireless, Crickett",
        "Contact_Type": "Expenditure",
        "ReportId": "2410",
        "Report_Type": "January 15: Semi-Annual 2022",
        "Amount": 225.0,
        "Recipient": "Carolyn Arnold",
        "Transaction_Date": "8/15/2021",
        "Date_Time_Submitted": "1/18/2022 3:34:32 PM",
        "Address": "3200  S. Lancaster\nDallas, TX    75216"
    },
    {
        "Report": "https://campfin.dallascityhall.com/FinalReports/tec0000001848_20190426_161641.pdf",
        "S/R": "https://campfin.dallascityhall.com/FinalReports/srp0000001848_20190426_161641.pdf",
        "Name": "Wireless, Crickett",
        "Contact_Type": "Expenditure",
        "ReportId": "1848",
        "Report_Type": "8th Day Before General Election 2019",
        "Amount": 135.0,
        "Recipient": "Carolyn Arnold",
        "Transaction_Date": "4/24/2019",
        "Date_Time_Submitted": "4/26/2019 4:16:41 PM",
        "Address": "3306  W. Camp Wisdom\nDallas, TX    75232"
    },
    {
        "Report": "N/A",
        "S/R": "https://campfin.dallascityhall.com/FinalReports/srp0000002185_20210401_165710.pdf",
        "Name": "Wireless, Crickett",
        "Contact_Type": "Expenditure",
        "ReportId": "2185",
        "Report_Type": "30th Day Before General Election 2021",
        "Amount": 375.0,
        "Recipient": "Carolyn KIng Arnold",
        "Transaction_Date": "3/15/2021",
        "Date_Time_Submitted": "4/1/2021 4:57:10 PM",
        "Address": "3306  West Camp Wisdom\nDallas, TX    75237"
    },
    {
        "Report": "https://campfin.dallascityhall.com/FinalReports/tec0000001746_20190404_113156.pdf",
        "S/R": "https://campfin.dallascityhall.com/FinalReports/srp0000001746_20190404_113156.pdf",
        "Name": "Wright, Al",
        "Contact_Type": "Expenditure",
        "ReportId": "1746",
        "Report_Type": "30th Day Before General Election 2019",
        "Amount": 1600.0,
        "Recipient": "Carolyn Arnold",
        "Transaction_Date": "3/1/2019",
        "Date_Time_Submitted": "4/4/2019 11:31:56 AM",
        "Address": "3440  Polk\nDallas, TX    75224"
    },
    {
        "Report": "https://campfin.dallascityhall.com/FinalReports/caf0000001893_20230207_171146.pdf",
        "S/R": "https://campfin.dallascityhall.com/FinalReports/src0000001893_20230207_171146.pdf",
        "Name": "Wright, Al",
        "Contact_Type": "Expenditure",
        "ReportId": "1893",
        "Report_Type": "July 15: Semi-Annual 2019\nCorrection Affidavit",
        "Amount": 1600.0,
        "Recipient": "Carolyn Arnold",
        "Transaction_Date": "6/12/2019",
        "Date_Time_Submitted": "2/7/2023 5:12:16 PM",
        "Address": "3440  S. Polk\nDallas, TX    75224"
    }
]