{
    "candidate_info": {
        "first_name": "Chad",
        "last_name": "West",
        "office_sought": "Council Distr ict 1",
        "report_totals": {
            "TOTAL OFFICEHOLDER CONTRIBUTIONS OF $50 OR LESS (OTHER THAN PLEDGES, LOANS, OR GUARANTEES OF LOANS), UNLESS ITEMIZED": 0.0,
            "TOTAL OFFICEHOLDER CONTRIBUTIONS OTHER THAN PLEDGES, LOANS, OR GUARANTEES OF LOANS)": 0.0,
            "TOTAL OFFICEHOLDER EXPENDITURES OF $100 OR LESS, UNLESS ITEMIZED": 0.0,
            "TOTAL OFFICEHOLDER EXPENDITURES": 0.0,
            "TOTAL POLITICAL CONTRIBUTIONS OF $50 OR LESS (OTHER THAN PLEDGES LOANS, OR GUARANTEES OF LOANS), UNLESS ITEMIZED": 0.0,
            "TOTAL POLITICAL CONTRIBUTIONS (OTHER THAN PLEDGES, LOANS, OR GUARANTEES OF LOANS)": 7744.4,
            "TOTAL POLITICAL EXPENDITURES OF $100 OR LESS UNLESS ITEMIZED": 0.0,
            "TOTAL POLITICAL EXPENDITURES": 62903.8
        }
    },
    "report_totals": {},
    "contributions": [
        {
            "Transaction_Date": "04/27/2021",
            "Name": "Michael Barnett",
            "Address": "4416 Potomac Ave Dallas, TX 75205",
            "Amount": 500.0,
            "Transaction_Type": "Campaign Contribution"
        },
        {
            "Transaction_Date": "04/26/2021",
            "Name": "Thomas Brown",
            "Address": "10540 20th Avenue NE Seattle, WA 98125",
            "Amount": 25.0,
            "Transaction_Type": "Campaign Contribution"
        },
        {
            "Transaction_Date": "04/26/2021",
            "Name": "Joel Burns",
            "Address": "2420 Adams Street Fort Worth, TX 76110",
            "Amount": 474.7,
            "Transaction_Type": "Campaign Contribution"
        },
        {
            "Transaction_Date": "04/26/2021",
            "Name": "Tirey Counts",
            "Address": "5535 Memorial Dr Suite F316 Houston, TX 77077",
            "Amount": 100.0,
            "Transaction_Type": "Campaign Contribution"
        },
        {
            "Transaction_Date": "04/30/2021",
            "Name": "Socorro Dinsmore",
            "Address": "1860 Masters Drive Desoto, TX 75115",
            "Amount": 1000.0,
            "Transaction_Type": "Campaign Contribution"
        },
        {
            "Transaction_Date": "04/27/2021",
            "Name": "Harryette Ehrhardt",
            "Address": "3525 Turtle Creek Blvd Suite 8A Dallas, TX 75219",
            "Amount": 250.0,
            "Transaction_Type": "Campaign Contribution"
        },
        {
            "Transaction_Date": "04/29/2021",
            "Name": "Raul Estrada",
            "Address": "1636 Cedar Hill Ave Dallas, TX 75208",
            "Amount": 1000.0,
            "Transaction_Type": "Campaign Contribution"
        },
        {
            "Transaction_Date": "04/26/2021",
            "Name": "Kyle Feerari",
            "Address": "1017 N. Main Avenue San Antonio, TX 78212",
            "Amount": 500.0,
            "Transaction_Type": "Campaign Contribution"
        },
        {
            "Transaction_Date": "04/26/2021",
            "Name": "Desiree Luckey",
            "Address": "1714 West Virginia Avenue Suite 3 Washington, DC 20002",
            "Amount": 25.0,
            "Transaction_Type": "Campaign Contribution"
        },
        {
            "Transaction_Date": "04/26/2021",
            "Name": "Timothy Meinke",
            "Address": "113 U Street NW Washington, DC 20001",
            "Amount": 25.0,
            "Transaction_Type": "Campaign Contribution"
        },
        {
            "Transaction_Date": "04/27/2021",
            "Name": "Bridget Moreno-Lopez",
            "Address": "2777 N Stemmons Frwy Suite 1000 Dallas, TX 75207",
            "Amount": 1000.0,
            "Transaction_Type": "Campaign Contribution"
        },
        {
            "Transaction_Date": "04/27/2021",
            "Name": "Jimmy OReilly",
            "Address": "3525 Turtle Creek Blvd Suite 20BC Dallas, TX 75219",
            "Amount": 500.0,
            "Transaction_Type": "Campaign Contribution"
        },
        {
            "Transaction_Date": "04/26/2021",
            "Name": "Ray Purser",
            "Address": "1208 Axis Ridge New Braunfels, TX 78131",
            "Amount": 100.0,
            "Transaction_Type": "Campaign Contribution"
        },
        {
            "Transaction_Date": "04/26/2021",
            "Name": "George Quesada",
            "Address": "3811 Turtle Creek Blvd Suite 1400 Dallas, TX 75219",
            "Amount": 1000.0,
            "Transaction_Type": "Campaign Contribution"
        },
        {
            "Transaction_Date": "04/27/2021",
            "Name": "Raymond Scott",
            "Address": "4144 N Central Exprwy Suite 250 Dallas, TX 75204",
            "Amount": 500.0,
            "Transaction_Type": "Campaign Contribution"
        },
        {
            "Transaction_Date": "04/30/2021",
            "Name": "Henry Shine",
            "Address": "1140 N Wells Street Chicago, IL 60610",
            "Amount": 50.0,
            "Transaction_Type": "Campaign Contribution"
        },
        {
            "Transaction_Date": "04/26/2021",
            "Name": "Stephen Skinner",
            "Address": "2633 NE 14th Ave Suite 107 Wilton Manors, FL 33334",
            "Amount": 94.7,
            "Transaction_Type": "Campaign Contribution"
        },
        {
            "Transaction_Date": "04/26/2021",
            "Name": "Carlton Smith",
            "Address": "P.O. Box 63 Holly Springs, MS 38635",
            "Amount": 100.0,
            "Transaction_Type": "Campaign Contribution"
        },
        {
            "Transaction_Date": "04/30/2021",
            "Name": "Chuck Space",
            "Address": "4600 Spicewood Springs Suite 103 Austin, TX 78759",
            "Amount": 250.0,
            "Transaction_Type": "Campaign Contribution"
        },
        {
            "Transaction_Date": "04/26/2021",
            "Name": "PAC - Stonewall Democrats of Dallas",
            "Address": "P.O. Box 192305 Dallas, TX 75219",
            "Amount": 250.0,
            "Transaction_Type": "Campaign Contribution"
        }
    ],
    "expenditures": [
        {
            "Transaction_Date": "04/22/2021",
            "Name": "Liz Miller",
            "Address": "1201 Bittern Drive Little Elm, TX 75068",
            "Amount": 119.08,
            "Transaction_Type": "Campaign Funds for Campaign Expenditures",
            "Category": "Advertising Expense",
            "Description": "Reimbursement for Stickers"
        },
        {
            "Transaction_Date": "04/22/2021",
            "Name": "Qualigraphics, Inc",
            "Address": "934 Stevens Woods CourDtallas, TX 75208",
            "Amount": 1161.91,
            "Transaction_Type": "Campaign Funds for Campaign Expenditures",
            "Category": "Advertising Expense",
            "Description": "Yard Signs and Stakes"
        },
        {
            "Transaction_Date": "04/23/2021",
            "Name": "Benny Guzman",
            "Address": "1147 North Madison Dallas, TX 75208",
            "Amount": 34.1,
            "Transaction_Type": "Campaign Funds for Campaign Expenditures",
            "Category": "Advertising Expense",
            "Description": "Reimbursement"
        },
        {
            "Transaction_Date": "04/23/2021",
            "Name": "Carla McKinzie",
            "Address": "Dallas, TX 75208",
            "Amount": 135.0,
            "Transaction_Type": "Campaign Funds for Campaign Expenditures",
            "Category": "Contract Labor",
            "Description": "Volunteer Help"
        },
        {
            "Transaction_Date": "04/26/2021",
            "Name": "Liz Miller",
            "Address": "1201 Bittern Drive Little Elm, TX 75068",
            "Amount": 250.48,
            "Transaction_Type": "Campaign Funds for Campaign Expenditures",
            "Category": "Advertising Expense",
            "Description": "Reimbursement"
        },
        {
            "Transaction_Date": "04/27/2021",
            "Name": "Liz Miller",
            "Address": "1201 Bittern Drive Little Elm, TX 75068",
            "Amount": 184.98,
            "Transaction_Type": "Campaign Funds for Campaign Expenditures",
            "Category": "Advertising Expense",
            "Description": "AirBnB Reimbursement"
        },
        {
            "Transaction_Date": "04/27/2021",
            "Name": "Chad West, PLLC",
            "Address": "3606 South Tyler Street Dallas, TX 75224",
            "Amount": 55.0,
            "Transaction_Type": "Campaign Funds for Campaign Expenditures",
            "Category": "Advertising Expense",
            "Description": "Reimbursement for Stamps"
        },
        {
            "Transaction_Date": "04/27/2021",
            "Name": "Full Moon Design Group, Inc",
            "Address": "P.O. Box 152020 Austin, TX 78715",
            "Amount": 595.38,
            "Transaction_Type": "Campaign Funds for Campaign Expenditures",
            "Category": "Advertising Expense",
            "Description": "Campaign Mailers and Website Edits"
        },
        {
            "Transaction_Date": "04/28/2021",
            "Name": "Chad West, PLLC",
            "Address": "3606 South Tyler Street Dallas, TX 75224",
            "Amount": 31.27,
            "Transaction_Type": "Campaign Funds for Campaign Expenditures",
            "Category": "Advertising Expense",
            "Description": "1/3 Mailchimp Reimbursement"
        },
        {
            "Transaction_Date": "04/29/2021",
            "Name": "Benjamin Calhoun",
            "Address": "Melissa, TX 75454",
            "Amount": 23.38,
            "Transaction_Type": "Campaign Funds for Campaign Expenditures",
            "Category": "Contract Labor",
            "Description": "Reimbursement"
        },
        {
            "Transaction_Date": "04/29/2021",
            "Name": "Benny Guzman",
            "Address": "1147 North Madison Dallas, TX 75208",
            "Amount": 112.5,
            "Transaction_Type": "Campaign Funds for Campaign Expenditures",
            "Category": "Contract Labor",
            "Description": "Volunteer Help"
        },
        {
            "Transaction_Date": "04/29/2021",
            "Name": "Hilda Duarte",
            "Address": "3312 Destiny Way Dallas, TX 75237",
            "Amount": 502.5,
            "Transaction_Type": "Campaign Funds for Campaign Expenditures",
            "Category": "Contract Labor",
            "Description": "Volunteer Help"
        },
        {
            "Transaction_Date": "04/29/2021",
            "Name": "Erick Mendoza",
            "Address": "Royce City, TX 75189",
            "Amount": 431.25,
            "Transaction_Type": "Campaign Funds for Campaign Expenditures",
            "Category": "Contract Labor",
            "Description": "Volunteer Help"
        },
        {
            "Transaction_Date": "04/29/2021",
            "Name": "Benjamin Calhoun",
            "Address": "Melissa, TX 75454",
            "Amount": 890.0,
            "Transaction_Type": "Campaign Funds for Campaign Expenditures",
            "Category": "Contract Labor",
            "Description": "Volunteer Help"
        },
        {
            "Transaction_Date": "04/29/2021",
            "Name": "Shannon Koenn",
            "Address": "3905 Coronado Drive Plano, TX 75074",
            "Amount": 648.5,
            "Transaction_Type": "Campaign Funds for Campaign Expenditures",
            "Category": "Contract Labor",
            "Description": "Volunteer Help"
        },
        {
            "Transaction_Date": "04/29/2021",
            "Name": "Nedra Cameron",
            "Address": "1311 Marvin Gardens Lancaster, TX 75134",
            "Amount": 191.25,
            "Transaction_Type": "Campaign Funds for Campaign Expenditures",
            "Category": "Contract Labor",
            "Description": "Volunteer Help"
        },
        {
            "Transaction_Date": "04/29/2021",
            "Name": "Edgar Johnson",
            "Address": "Dallas, TX 75237",
            "Amount": 958.0,
            "Transaction_Type": "Campaign Funds for Campaign Expenditures",
            "Category": "Contract Labor",
            "Description": "Volunteer Help"
        },
        {
            "Transaction_Date": "04/29/2021",
            "Name": "Liz Miller",
            "Address": "1201 Bittern Drive Little Elm, TX 75068",
            "Amount": 1154.13,
            "Transaction_Type": "Campaign Funds for Campaign Expenditures",
            "Category": "Contract Labor",
            "Description": "Volunteer Help and Reimbursement"
        },
        {
            "Transaction_Date": "04/29/2021",
            "Name": "Vanessa Ugorji",
            "Address": "Arlington, TX 76013",
            "Amount": 469.95,
            "Transaction_Type": "Campaign Funds for Campaign Expenditures",
            "Category": "Contract Labor",
            "Description": "Volunteer Help"
        },
        {
            "Transaction_Date": "04/29/2021",
            "Name": "Joshua Bodwin",
            "Address": "Arlington, TX 76013",
            "Amount": 637.5,
            "Transaction_Type": "Campaign Funds for Campaign Expenditures",
            "Category": "Contract Labor",
            "Description": "Volunteer Help"
        },
        {
            "Transaction_Date": "04/29/2021",
            "Name": "EcoLatino",
            "Address": "3606 S Tyler Street Dallas, TX 75224",
            "Amount": 499.0,
            "Transaction_Type": "Campaign Funds for Campaign Expenditures",
            "Category": "Advertising Expense",
            "Description": "Marketing"
        },
        {
            "Transaction_Date": "04/30/2021",
            "Name": "Benny Guzman",
            "Address": "1147 North Madison Dallas, TX 75208",
            "Amount": 62.5,
            "Transaction_Type": "Campaign Funds for Campaign Expenditures",
            "Category": "Contract Labor",
            "Description": "Volunteer Help"
        },
        {
            "Transaction_Date": "04/30/2021",
            "Name": "Chad West",
            "Address": "810 North Bishop AvenuDeallas, TX 75208",
            "Amount": 1434.57,
            "Transaction_Type": "Campaign Funds for Campaign Expenditures",
            "Category": "Contract Labor",
            "Description": "Volunteer Meals Reimbursement"
        },
        {
            "Transaction_Date": "04/30/2021",
            "Name": "Kiers Hope Foundation",
            "Address": "P.O. Box 2586 Cedar Hill, TX 75106",
            "Amount": 500.0,
            "Transaction_Type": "Campaign Funds for Campaign Expenditures",
            "Category": "Advertising Expense",
            "Description": "Sponsorship"
        },
        {
            "Transaction_Date": "04/30/2021",
            "Name": "Qualigraphics, Inc",
            "Address": "934 Stevens Woods CourDtallas, TX 75208",
            "Amount": 1317.95,
            "Transaction_Type": "Campaign Funds for Campaign Expenditures",
            "Category": "Advertising Expense",
            "Description": "Car Magnet and Sierra Club Signs"
        },
        {
            "Transaction_Date": "05/03/2021",
            "Name": "Taylor Adams",
            "Address": "Dallas, TX 75208",
            "Amount": 2000.0,
            "Transaction_Type": "Campaign Funds for Campaign Expenditures",
            "Category": "Advertising Expense",
            "Description": "Consulting"
        },
        {
            "Transaction_Date": "05/03/2021",
            "Name": "Susan Craig",
            "Address": "3606 S Tyler Street Dallas, TX 75224",
            "Amount": 315.0,
            "Transaction_Type": "Campaign Funds for Campaign Expenditures",
            "Category": "Contract Labor",
            "Description": "Volunteer Help"
        },
        {
            "Transaction_Date": "05/03/2021",
            "Name": "Nedra Cameron",
            "Address": "1311 Marvin Gardens Lancaster, TX 75134",
            "Amount": 112.5,
            "Transaction_Type": "Campaign Funds for Campaign Expenditures",
            "Category": "Contract Labor",
            "Description": "Volunteer Help"
        },
        {
            "Transaction_Date": "05/04/2021",
            "Name": "Edgar Johnson",
            "Address": "Dallas, TX 75237",
            "Amount": 798.0,
            "Transaction_Type": "Campaign Funds for Campaign Expenditures",
            "Category": "Contract Labor",
            "Description": "Volunteer Help"
        },
        {
            "Transaction_Date": "05/04/2021",
            "Name": "Jesse Perez",
            "Address": "3606 S Tyler Street Dallas, TX 75224",
            "Amount": 300.0,
            "Transaction_Type": "Campaign Funds for Campaign Expenditures",
            "Category": "Contract Labor",
            "Description": "Lawn Mowed"
        },
        {
            "Transaction_Date": "05/05/2021",
            "Name": "Liz Miller",
            "Address": "1201 Bittern Drive Little Elm, TX 75068",
            "Amount": 1050.0,
            "Transaction_Type": "Campaign Funds for Campaign Expenditures",
            "Category": "Contract Labor",
            "Description": "Volunteer Help"
        },
        {
            "Transaction_Date": "05/05/2021",
            "Name": "Benjamin Calhoun",
            "Address": "Melissa, TX 75454",
            "Amount": 710.0,
            "Transaction_Type": "Campaign Funds for Campaign Expenditures",
            "Category": "Contract Labor",
            "Description": "Volunteer Help"
        },
        {
            "Transaction_Date": "05/05/2021",
            "Name": "Benny Guzman",
            "Address": "1147 North Madison Dallas, TX 75208",
            "Amount": 120.0,
            "Transaction_Type": "Campaign Funds for Campaign Expenditures",
            "Category": "Contract Labor",
            "Description": "Poll Greeting"
        },
        {
            "Transaction_Date": "05/05/2021",
            "Name": "Benny Guzman",
            "Address": "1147 North Madison Dallas, TX 75208",
            "Amount": 40.0,
            "Transaction_Type": "Campaign Funds for Campaign Expenditures",
            "Category": "Advertising Expense",
            "Description": "Donation"
        },
        {
            "Transaction_Date": "05/06/2021",
            "Name": "Jesse Perez",
            "Address": "3606 S Tyler Street Dallas, TX 75224",
            "Amount": 532.12,
            "Transaction_Type": "Campaign Funds for Campaign Expenditures",
            "Category": "Advertising Expense",
            "Description": "Reimbursement for Poles"
        },
        {
            "Transaction_Date": "05/06/2021",
            "Name": "Katy Seitzler",
            "Address": "217 Sycamore Creek RoaAdllen, TX 75002",
            "Amount": 1692.48,
            "Transaction_Type": "Campaign Funds for Campaign Expenditures",
            "Category": "Advertising Expense",
            "Description": "Media"
        },
        {
            "Transaction_Date": "05/06/2021",
            "Name": "Joshua Bodwin",
            "Address": "Arlington, TX 76013",
            "Amount": 307.5,
            "Transaction_Type": "Campaign Funds for Campaign Expenditures",
            "Category": "Contract Labor",
            "Description": "Volunteer"
        },
        {
            "Transaction_Date": "05/06/2021",
            "Name": "Erick Mendoza",
            "Address": "Royce City, TX 75189",
            "Amount": 307.5,
            "Transaction_Type": "Campaign Funds for Campaign Expenditures",
            "Category": "Contract Labor",
            "Description": "Volunteer"
        },
        {
            "Transaction_Date": "05/06/2021",
            "Name": "Shannon Koenn",
            "Address": "3905 Coronado Drive Plano, TX 75074",
            "Amount": 461.25,
            "Transaction_Type": "Campaign Funds for Campaign Expenditures",
            "Category": "Contract Labor",
            "Description": "Volunteer"
        },
        {
            "Transaction_Date": "05/10/2021",
            "Name": "John Sims",
            "Address": "2103 Balboa Dallas, TX 75224",
            "Amount": 250.0,
            "Transaction_Type": "Campaign Funds for Campaign Expenditures",
            "Category": "Advertising Expense",
            "Description": "DJ"
        },
        {
            "Transaction_Date": "05/10/2021",
            "Name": "John Sims",
            "Address": "2103 Balboa Dallas, TX 75224",
            "Amount": 100.0,
            "Transaction_Type": "Campaign Funds for Campaign Expenditures",
            "Category": "Advertising Expense",
            "Description": "DJ"
        },
        {
            "Transaction_Date": "05/11/2021",
            "Name": "Jesse Perez",
            "Address": "3606 S Tyler Street Dallas, TX 75224",
            "Amount": 1702.25,
            "Transaction_Type": "Campaign Funds for Campaign Expenditures",
            "Category": "Contract Labor",
            "Description": "Volunteer Help and Signs Pick up"
        },
        {
            "Transaction_Date": "05/12/2021",
            "Name": "Dallas Voice",
            "Address": "Dallas, TX 75207",
            "Amount": 598.0,
            "Transaction_Type": "Campaign Funds for Campaign Expenditures",
            "Category": "Advertising Expense",
            "Description": "Ad Display"
        },
        {
            "Transaction_Date": "05/12/2021",
            "Name": "Qualigraphics, Inc",
            "Address": "934 Stevens Woods CourDtallas, TX 75208",
            "Amount": 1047.88,
            "Transaction_Type": "Campaign Funds for Campaign Expenditures",
            "Category": "Advertising Expense",
            "Description": "Mardi Gras Beads w/Medallion"
        },
        {
            "Transaction_Date": "05/12/2021",
            "Name": "Hilda Duarte",
            "Address": "3312 Destiny Way Dallas, TX 75237",
            "Amount": 135.0,
            "Transaction_Type": "Campaign Funds for Campaign Expenditures",
            "Category": "Contract Labor",
            "Description": "Poll Greeting"
        },
        {
            "Transaction_Date": "05/12/2021",
            "Name": "Chad West, PLLC",
            "Address": "3606 South Tyler Street Dallas, TX 75224",
            "Amount": 31.26,
            "Transaction_Type": "Campaign Funds for Campaign Expenditures",
            "Category": "Advertising Expense",
            "Description": "1/3 Mailchimp Reimbursement"
        },
        {
            "Transaction_Date": "05/12/2021",
            "Name": "Oak Cliff Lions Club",
            "Address": "P.O. Box 4445 Dallas, TX 75208",
            "Amount": 25.0,
            "Transaction_Type": "Campaign Funds for Campaign Expenditures",
            "Category": "Advertising Expense",
            "Description": "Membership Fees"
        },
        {
            "Transaction_Date": "05/13/2021",
            "Name": "Jesse Perez",
            "Address": "3606 S Tyler Street Dallas, TX 75224",
            "Amount": 1290.0,
            "Transaction_Type": "Campaign Funds for Campaign Expenditures",
            "Category": "Contract Labor",
            "Description": "Volunteer"
        },
        {
            "Transaction_Date": "05/14/2021",
            "Name": "Victoria Perez",
            "Address": "808 Rutherford Road Waxahachie, TX 75165",
            "Amount": 500.0,
            "Transaction_Type": "Campaign Funds for Campaign Expenditures",
            "Category": "Contract Labor",
            "Description": "Wages"
        },
        {
            "Transaction_Date": "05/14/2021",
            "Name": "Benny Guzman",
            "Address": "1147 North Madison Dallas, TX 75208",
            "Amount": 500.0,
            "Transaction_Type": "Campaign Funds for Campaign Expenditures",
            "Category": "Contract Labor",
            "Description": "Wages"
        },
        {
            "Transaction_Date": "05/14/2021",
            "Name": "Benny Guzman",
            "Address": "1147 North Madison Dallas, TX 75208",
            "Amount": 105.0,
            "Transaction_Type": "Campaign Funds for Campaign Expenditures",
            "Category": "Contract Labor",
            "Description": "Volunteer Help"
        },
        {
            "Transaction_Date": "05/14/2021",
            "Name": "Jesse Perez",
            "Address": "3606 S Tyler Street Dallas, TX 75224",
            "Amount": 500.0,
            "Transaction_Type": "Campaign Funds for Campaign Expenditures",
            "Category": "Contract Labor",
            "Description": "Wages"
        },
        {
            "Transaction_Date": "05/14/2021",
            "Name": "Katy Seitzler",
            "Address": "217 Sycamore Creek RoaAdllen, TX 75002",
            "Amount": 500.0,
            "Transaction_Type": "Campaign Funds for Campaign Expenditures",
            "Category": "Contract Labor",
            "Description": "Wages"
        },
        {
            "Transaction_Date": "05/14/2021",
            "Name": "Edgar Johnson",
            "Address": "Chicago, IL 60637",
            "Amount": 350.0,
            "Transaction_Type": "Campaign Funds for Campaign Expenditures",
            "Category": "Contract Labor",
            "Description": "Wages"
        },
        {
            "Transaction_Date": "05/14/2021",
            "Name": "Taylor Adams",
            "Address": "Dallas, TX 75208",
            "Amount": 2000.0,
            "Transaction_Type": "Campaign Funds for Campaign Expenditures",
            "Category": "Contract Labor",
            "Description": "Wages"
        },
        {
            "Transaction_Date": "05/14/2021",
            "Name": "Anna Casey",
            "Address": "3606 S Tyler Street Dallas, TX 75224",
            "Amount": 5000.0,
            "Transaction_Type": "Campaign Funds for Campaign Expenditures",
            "Category": "Contract Labor",
            "Description": "Wages"
        },
        {
            "Transaction_Date": "05/14/2021",
            "Name": "Anna Casey",
            "Address": "3606 S Tyler Street Dallas, TX 75224",
            "Amount": 20000.0,
            "Transaction_Type": "Campaign Funds for Campaign Expenditures",
            "Category": "Advertising Expense",
            "Description": "Consulting Fees"
        },
        {
            "Transaction_Date": "05/18/2021",
            "Name": "Qualigraphics, Inc",
            "Address": "934 Stevens Woods CourDtallas, TX 75208",
            "Amount": 545.35,
            "Transaction_Type": "Campaign Funds for Campaign Expenditures",
            "Category": "Advertising Expense",
            "Description": "Slap Bracelet"
        },
        {
            "Transaction_Date": "05/19/2021",
            "Name": "Vanessa Ugorji",
            "Address": "Arlington, TX 76013",
            "Amount": 435.0,
            "Transaction_Type": "Campaign Funds for Campaign Expenditures",
            "Category": "Contract Labor",
            "Description": "Volunteer Help"
        },
        {
            "Transaction_Date": "05/20/2021",
            "Name": "Susan Craig",
            "Address": "3606 South Tyler Street Dallas, TX 75224",
            "Amount": 150.0,
            "Transaction_Type": "Campaign Funds for Campaign Expenditures",
            "Category": "Advertising Expense",
            "Description": "Donation"
        },
        {
            "Transaction_Date": "05/25/2021",
            "Name": "Chad West",
            "Address": "3606 South Tyler Street Dallas, TX 75224",
            "Amount": 630.14,
            "Transaction_Type": "Campaign Funds for Campaign Expenditures",
            "Category": "Advertising Expense",
            "Description": "Reimbursement"
        },
        {
            "Transaction_Date": "05/24/2021",
            "Name": "The Kessler School",
            "Address": "1215 Turner Avenue Dallas, TX 75208",
            "Amount": 1000.0,
            "Transaction_Type": "Campaign Funds for Campaign Expenditures",
            "Category": "Advertising Expense",
            "Description": "Sponsor"
        },
        {
            "Transaction_Date": "06/01/2021",
            "Name": "Qualigraphics, Inc",
            "Address": "934 Stevens Woods CourDtallas, TX 75208",
            "Amount": 1165.16,
            "Transaction_Type": "Campaign Funds for Campaign Expenditures",
            "Category": "Advertising Expense",
            "Description": "Yard Signs"
        },
        {
            "Transaction_Date": "06/04/2021",
            "Name": "Oak Cliff Lions",
            "Address": "P.O. Box 4445 Dallas, TX 75208",
            "Amount": 25.0,
            "Transaction_Type": "Campaign Funds for Campaign Expenditures",
            "Category": "Advertising Expense",
            "Description": "Membership Fees"
        },
        {
            "Transaction_Date": "06/04/2021",
            "Name": "LGBT Chamber of Commerce Foundation",
            "Address": "Dallas, TX 75219",
            "Amount": 1000.0,
            "Transaction_Type": "Campaign Funds for Campaign Expenditures",
            "Category": "Advertising Expense",
            "Description": "Sponsor"
        },
        {
            "Transaction_Date": "06/08/2021",
            "Name": "Rulli Torres",
            "Address": "Dallas, TX 75201",
            "Amount": 150.0,
            "Transaction_Type": "Campaign Funds for Campaign Expenditures",
            "Category": "Advertising Expense",
            "Description": "Rulli Pink Show Sponsor"
        },
        {
            "Transaction_Date": "06/11/2021",
            "Name": "Benny Guzman",
            "Address": "1147 North Madison Dallas, TX 75208",
            "Amount": 100.0,
            "Transaction_Type": "Campaign Funds for Campaign Expenditures",
            "Category": "Advertising Expense",
            "Description": "Reimbursement"
        },
        {
            "Transaction_Date": "06/14/2021",
            "Name": "The 23rd Senatorial District",
            "Address": "P.O. Box 226534 Dallas, TX 75220",
            "Amount": 15.0,
            "Transaction_Type": "Campaign Funds for Campaign Expenditures",
            "Category": "Advertising Expense",
            "Description": "Membership Fees"
        },
        {
            "Transaction_Date": "06/14/2021",
            "Name": "Chad West, PLLC",
            "Address": "3606 South Tyler Street Dallas, TX 75224",
            "Amount": 31.26,
            "Transaction_Type": "Campaign Funds for Campaign Expenditures",
            "Category": "Advertising Expense",
            "Description": "1/3 Mailchimp Reimbursement"
        },
        {
            "Transaction_Date": "06/14/2021",
            "Name": "Camp Wisdom UMC",
            "Address": "Dallas, TX 75232",
            "Amount": 150.0,
            "Transaction_Type": "Campaign Funds for Campaign Expenditures",
            "Category": "Advertising Expense",
            "Description": "Tennis Exhibition Donation"
        },
        {
            "Transaction_Date": "06/24/2021",
            "Name": "Chad West, PLLC",
            "Address": "3606 South Tyler Street Dallas, TX 75224",
            "Amount": 31.27,
            "Transaction_Type": "Campaign Funds for Campaign Expenditures",
            "Category": "Advertising Expense",
            "Description": "1/3 Mailchimp Reimbursement"
        },
        {
            "Transaction_Date": "06/29/2021",
            "Name": "Chad West",
            "Address": "3606 South Tyler Street Dallas, TX 75224",
            "Amount": 1663.43,
            "Transaction_Type": "Campaign Funds for Campaign Expenditures",
            "Category": "Advertising Expense",
            "Description": "Reimbursement"
        },
        {
            "Transaction_Date": "06/29/2021",
            "Name": "Chad West Chad West, PLLC",
            "Address": "3606 South Tyler Street Dallas, TX 75224",
            "Amount": 31.27,
            "Transaction_Type": "Campaign Funds for Campaign Expenditures",
            "Category": "Advertising Expense",
            "Description": "1/3 Mailchimp Reimbursement"
        }
    ]
}